setup.py
Power3D/__init__.py
Power3D.egg-info/PKG-INFO
Power3D.egg-info/SOURCES.txt
Power3D.egg-info/dependency_links.txt
Power3D.egg-info/top_level.txt