Metadata-Version: 1.0
Name: Power3D
Version: 1.1
Summary: OpenGL helper library making it easy to create 3D games in python!
